resilipy/__init__.py
resilipy/__main__.py
resilipy/models/XGBoost C57 mice.model
resilipy/scripts/__init__.py
resilipy/scripts/buider.py
resilipy/scripts/dataframe_reader.py
resilipy/scripts/labeler.py
resilipy/scripts/preprocessor.py
resilipy/scripts/save_model.py
resilipy/ui/builder.ui
resilipy/ui/labeler.ui
resilipy/ui/preprocessor.ui
resilipy/ui/resilipy.ui
resilipy/ui/stylesheet.txt
resilipy-0.1.0.dist-info/LICENSE
resilipy-0.1.0.dist-info/METADATA
resilipy-0.1.0.dist-info/WHEEL
resilipy-0.1.0.dist-info/top_level.txt
resilipy-0.1.0.dist-info/RECORD
