Metadata-Version: 2.1
Name: resilipy
Version: 0.1.0
Summary: ResiliPy - A machine-learning based Mouse labelling GUI.
Home-page: https://github.com/dietvin/resilipy
Author: Vincent Dietrich
Author-email: vdietric@students.uni-mainz.de
License: MIT
Classifier: License :: OSI Approved :: MIT License
Classifier: Operating System :: OS Independent
Classifier: Programming Language :: Python
Classifier: Topic :: Scientific/Engineering :: Bio-Informatics
Requires-Python: >=3.8
License-File: LICENSE
Requires-Dist: PyQt6 (>=6.3.1)
Requires-Dist: xgboost (>=1.6.1)
Requires-Dist: scikit-learn (>=1.1.1)
Requires-Dist: numpy (>=1.23.1)
Requires-Dist: pandas (>=1.4.3)
Requires-Dist: openpyxl (>=3.0.10)
Requires-Dist: Levenshtein (>=0.20.1)
Requires-Dist: pyqtgraph (>=0.12.4)
